cc_engines/__init__.py
cc_engines/base.py
cc_engines/lc.py
cc_engines/maia_engine.py
cc_engines/model_utils.py
cc_engines/random_engine.py
cc_engines/stockfish_engine.py
cc_engines/utils.py
cc_engines/tests/__init__.py
cc_engines/tests/conftest.py
cc_engines/tests/test_base.py
cc_engines/tests/test_integration.py
cc_engines/tests/test_maia.py
cc_engines/tests/test_model_utils.py
cc_engines/tests/test_stock.py
cc_engines-0.1.0.dist-info/METADATA
cc_engines-0.1.0.dist-info/WHEEL
cc_engines-0.1.0.dist-info/top_level.txt
cc_engines-0.1.0.dist-info/RECORD
