Metadata-Version: 2.1
Name: cc_engines
Version: 0.1.0
Requires-Dist: chess
Requires-Dist: numpy
